jaaql/__init__.py
jaaql/config_constants.py
jaaql/constants.py
jaaql/generated_constants.py
jaaql/jaaql.py
jaaql/patch.py
jaaql/config/__init__.py
jaaql/config/config-docker.ini
jaaql/config/config-test.ini
jaaql/config/config.ini
jaaql/db/__init__.py
jaaql/db/db_interface.py
jaaql/db/db_pg_interface.py
jaaql/db/db_utils.py
jaaql/db/db_utils_no_circ.py
jaaql/documentation/__init__.py
jaaql/documentation/documentation_internal.py
jaaql/documentation/documentation_public.py
jaaql/documentation/documentation_shared.py
jaaql/email/__init__.py
jaaql/email/email_manager.py
jaaql/email/email_manager_service.py
jaaql/email/patch_ems.py
jaaql/exceptions/__init__.py
jaaql/exceptions/custom_http_status.py
jaaql/exceptions/http_status_exception.py
jaaql/exceptions/jaaql_interpretable_handled_errors.py
jaaql/exceptions/not_yet_implement_exception.py
jaaql/interpreter/__init__.py
jaaql/interpreter/interpret_jaaql.py
jaaql/migrations/__init__.py
jaaql/migrations/migrations.py
jaaql/mvc/__init__.py
jaaql/mvc/base_controller.py
jaaql/mvc/base_model.py
jaaql/mvc/controller.py
jaaql/mvc/controller_interface.py
jaaql/mvc/exception_queries.py
jaaql/mvc/generated_queries.py
jaaql/mvc/handmade_queries.py
jaaql/mvc/model.py
jaaql/mvc/model_interface.py
jaaql/mvc/response.py
jaaql/openapi/__init__.py
jaaql/openapi/swagger_documentation.py
jaaql/scripts/01.install_domains.generated.sql
jaaql/scripts/02.install_super_user.exceptions.sql
jaaql/scripts/03.install_super_user.handwritten.sql
jaaql/scripts/04.install_jaaql_data_structures.generated.sql
jaaql/scripts/05.install_static_data.generated.sql
jaaql/scripts/06.install_jaaql.exceptions.sql
jaaql/scripts/ZZZZ.generated_functions_views_and_permissions.sql
jaaql/scripts/ZZZZ.reset_references.sql
jaaql/scripts/swagger_template.html
jaaql/services/__init__.py
jaaql/services/cached_canned_query_service.py
jaaql/services/migrations_manager_service.py
jaaql/services/patch_mms.py
jaaql/services/patch_shared_var_service.py
jaaql_middleware_python-4.34.2.dist-info/licenses/LICENSE.txt
jaaql_middleware_python-4.34.2.dist-info/METADATA
jaaql_middleware_python-4.34.2.dist-info/WHEEL
jaaql_middleware_python-4.34.2.dist-info/top_level.txt
jaaql_middleware_python-4.34.2.dist-info/RECORD
