Metadata-Version: 2.4
Name: jaaql-middleware-python
Version: 4.34.2
Summary: The jaaql package, allowing for rapid development and deployment of RESTful HTTP applications
Home-page: https://github.com/JAAQL/JAAQL-middleware-python
Author: Software Quality Measurement and Improvement bv
Author-email: aaron.tasker@sqmi.nl
License: Mozilla Public License Version 2.0 with Commons Clause
License-File: LICENSE.txt
Requires-Dist: jaaql-monitor~=1.6.3
Requires-Dist: psycopg[binary]~=3.2.13
Requires-Dist: Pillow~=11.2.1
Requires-Dist: cryptography~=44.0.2
Requires-Dist: flask~=3.1.0
Requires-Dist: coverage~=7.4.3
Requires-Dist: psycopg-pool~=3.2.1
Requires-Dist: pyjwt~=2.10.1
Requires-Dist: pyyaml~=6.0.1
Requires-Dist: werkzeug~=3.1.3
Requires-Dist: argon2-cffi~=23.1.0
Requires-Dist: pyotp~=2.9.0
Requires-Dist: qrcode~=7.4.2
Requires-Dist: gunicorn~=23.0.0
Requires-Dist: gevent~=24.11.1
Requires-Dist: requests~=2.32.3
Requires-Dist: pyzbar~=0.1.9
Requires-Dist: parsys-requests-unixsocket~=0.3.2
Requires-Dist: selenium~=4.29.0
Requires-Dist: twine~=5.0.0
Requires-Dist: urllib3~=2.3.0
Requires-Dist: jwcrypto~=1.5.6
Requires-Dist: jinja2~=3.1.6
Requires-Dist: idna~=3.10
Requires-Dist: certifi~=2025.1.31
Dynamic: author
Dynamic: author-email
Dynamic: description
Dynamic: description-content-type
Dynamic: home-page
Dynamic: license
Dynamic: license-file
Dynamic: requires-dist
Dynamic: summary
